{
  "parent_document": {
    "filename": "日语化物语.pdf",
    "file_path": "src\\data\\source\\Japanese\\日语化物语.pdf",
    "total_pages": 10,
    "language": "Japanese",
    "total_chunks": 1,
    "processing_date": "2025-12-28 21:58:00"
  },
  "document_chunks": [
    {
      "id": "日语化物语_c001_p006_c000",
      "text": "本文に入っていきます。 謝罪ばかりでは致し方ありません。 どうか、どうか。 頭に浮かぶありったけの罵詈雑言を僕に。 ようか。この親不孝者をどうか、何卒、どうか、叱りつけてはくれないでし 行方不明となった兄に示しがつけられない限りです。 ってしまったのです。僕でさえさつぱりの出来事だった故に流されてこのようなことになゆえ 何を言っているのかさつぱりと思います。 のち深夜に家を出た後、化物の娘と『くちづけ』を致しました。 分自身でさえ存じ上げないことなのですが。ただ一時の気の迷いか、はたまた反抗心が生まれたからか、僕は自 がないほど健全に生きてきました。僕はこれまでに至極健康で思慮深く聡明に、一寸の罪も犯したこと 拝啓お父さん、お母さんへ。",
      "page_number": 6,
      "section_title": "01話 海月",
      "chunk_index": 0,
      "total_chunks_in_page": 1,
      "coordinates": {
        "x0": 520.0,
        "y0": 168.0,
        "x1": 548.0,
        "y1": 258.0
      },
      "text_hash": "7c4b335ff197f6ae"
    }
  ]
}